scclib/__init__.py
scclib/app.py
scclib/device.py
scclib/test_device.py
scclib-0.1.3.dist-info/LICENSE.md
scclib-0.1.3.dist-info/METADATA
scclib-0.1.3.dist-info/WHEEL
scclib-0.1.3.dist-info/top_level.txt
scclib-0.1.3.dist-info/RECORD
