Metadata-Version: 2.1
Name: scclib
Version: 0.1.3
Summary: Client library for S.C.I.L.E.R.
Home-page: https://github.com/IssaHanou/BEP_1920_Q2
Author: Raccoon Serious Games
Author-email: BEP@raccoon.games
License: UNKNOWN
Platform: UNKNOWN
Classifier: Programming Language :: Python :: 3
Classifier: License :: OSI Approved :: GNU General Public License v3 (GPLv3)
Classifier: Operating System :: OS Independent
Requires-Python: >=3.5
